gps_babel_tower/__init__.py
gps_babel_tower/models/__init__.py
gps_babel_tower/models/diffusion.py
gps_babel_tower/models/text_embedding.py
gps_babel_tower/models/text_embedding_pt.py
gps_babel_tower/tasks/__init__.py
gps_babel_tower/tasks/image_generation.py
gps_babel_tower/tasks/lang_detect.py
gps_babel_tower/tasks/text_cluster.py
gps_babel_tower/tasks/word_seg.py
gps_babel_tower/tasks/keyword_extraction/__init__.py
gps_babel_tower/tasks/keyword_extraction/keyword_extraction.py
gps_babel_tower/tasks/keyword_extraction/spacy_keyword_extraction.py
gps_babel_tower/tasks/language_detection/__init__.py
gps_babel_tower/tasks/language_detection/language_detection.py
gps_babel_tower/tasks/nearest_neighbor/__init__.py
gps_babel_tower/tasks/nearest_neighbor/nearest_neighbor.py
gps_babel_tower/tasks/sentiment/__init__.py
gps_babel_tower/tasks/sentiment/sentiment.py
gps_babel_tower/tasks/translation/__init__.py
gps_babel_tower/tasks/translation/translation.py
gps_babel_tower/utils/__init__.py
gps_babel_tower/utils/data_util.py
gps_babel_tower/utils/sheet_util.py
gps_babel_tower-0.1.1.dist-info/LICENSE
gps_babel_tower-0.1.1.dist-info/METADATA
gps_babel_tower-0.1.1.dist-info/WHEEL
gps_babel_tower-0.1.1.dist-info/top_level.txt
gps_babel_tower-0.1.1.dist-info/RECORD
